mwng/__init__.py
mwng/example.py
mwng-0.0.10.dist-info/LICENSE
mwng-0.0.10.dist-info/LICENSE_NOTICE.txt
mwng-0.0.10.dist-info/METADATA
mwng-0.0.10.dist-info/WHEEL
mwng-0.0.10.dist-info/top_level.txt
mwng-0.0.10.dist-info/RECORD
