Metadata-Version: 2.1
Name: mwng
Version: 0.0.10
Summary: MediaWiki API for Python 3
Home-page: https://github.com/Emojigit/mw
Author: Emojipypi
Author-email: yiufamily.hh@gmail.com
License: UNKNOWN
Project-URL: Bug Tracker, https://github.com/Emojigit/mw/issues
Platform: UNKNOWN
Classifier: Development Status :: 1 - Planning
Classifier: Intended Audience :: Other Audience
Classifier: Programming Language :: Python :: 3
Classifier: License :: OSI Approved :: GNU Lesser General Public License v2 or later (LGPLv2+)
Classifier: Operating System :: OS Independent
Classifier: Topic :: Internet :: WWW/HTTP :: Dynamic Content :: Wiki
Requires-Python: >=3.6
License-File: LICENSE
License-File: LICENSE_NOTICE.txt
Requires-Dist: requests
Requires-Dist: validators
